{
   "style" : "default",
   "config" : "save_yeyuanhuo.dat",
   "width" : 1000,
   "height" : 500,
   "cancelscroll" : true,
   "countdown" : 0,
	"bg" : "bg.jpg",
   "cancelname" : "返回",
   "okname" : "继续",
   "views" : [
	{
         "align" : "center",
         "color" : "0,0,0",
         "size" : "30",
         "text" : "业原火",
         "type" : "Label"
      },
      {
         "id" : "tan_",
         "width" : 1000,
         "height" : 50,
         "type" : "LinearLayout",
         "views" : [
            {
               "align" : "left",
               "color" : "0,0,0",
               "size" : "30",
               "text" : "贪之阵 - ",
               "type" : "Label",
               "width" : 670
            },
            {
               "id" : "round_tan",
               "list" : "0次,10次,20次,30次,50次,100次,全部贪券",
               "select" : "6",
               "size" : "22",
               "type" : "ComboBox",
               "width" : 250
            }
         ]
      },
	  {
         "id" : "chen_",
         "width" : 1000,
         "height" : 50,
         "type" : "LinearLayout",
         "views" : [
            {
               "align" : "left",
               "color" : "0,0,0",
               "size" : "30",
               "text" : "嗔之阵 - ",
               "type" : "Label",
               "width" : 670
            },
            {
               "id" : "round_chen",
               "list" : "0次,10次,20次,30次,50次,100次,全部嗔券",
               "select" : "6",
               "size" : "22",
               "type" : "ComboBox",
               "width" : 250
            }
         ]
      },
	  {
         "id" : "chi_",
         "width" : 1000,
         "height" : 50,
         "type" : "LinearLayout",
         "views" : [
            {
               "align" : "left",
               "color" : "0,0,0",
               "size" : "30",
               "text" : "痴之阵 - ",
               "type" : "Label",
               "width" : 670
            },
            {
               "id" : "round_chi",
               "list" : "0次,10次,20次,30次,50次,100次,全部痴券",
               "select" : "6",
               "size" : "22",
               "type" : "ComboBox",
               "width" : 250
            }
         ]
      },
	  {
         "id" : "lock",
         "list" : "锁定出战阵容(建议开启)",
         "select" : "0",
         "size" : "30",
         "type" : "CheckBoxGroup",
         "orientation" : "horizontal",
         "color" : "0,0,0"
      }
   ]
}